dash_builder/__init__.py
dash_builder/_dash_object.py
dash_builder/cli.py
dash_builder/dash_page.py
dash_builder/dash_view.py
dash_builder/examples/basic-mantine/app.py
dash_builder/examples/basic-mantine/pages/analytics.py
dash_builder/examples/basic-mantine/pages/home.py
dash_builder/examples/basic-mantine/pages/not_found_404.py
dash_builder/examples/basic-mantine/views/__init__.py
dash_builder/examples/basic-mantine/views/footer.py
dash_builder/examples/basic-mantine/views/header.py
dash_builder/examples/basic-mantine/views/sidebar.py
dash_builder/templates/__init__.py
dash_builder/templates/object_template.py
dash_builder/templates/page_template.py
dash_builder/templates/view_template.py
dash_builder-0.2.0.dist-info/METADATA
dash_builder-0.2.0.dist-info/WHEEL
dash_builder-0.2.0.dist-info/entry_points.txt
dash_builder-0.2.0.dist-info/licenses/LICENSE
dash_builder-0.2.0.dist-info/RECORD
