Metadata-Version: 2.4
Name: dash-builder
Version: 0.2.0
Summary: A tool and framework to simplify construction of Python Dash applications.
Author-email: robfs <robfoxsimms@gmail.com>
License-File: LICENSE
Requires-Python: >=3.10
Requires-Dist: dash-mantine-components>=0.15.3
Requires-Dist: dash>=2.18.2
Requires-Dist: rich>=13.9.4
Requires-Dist: typer>=0.15.1
Requires-Dist: typing-extensions>=4.12.2
